canfd/__init__.py
canfd/canfd.py
canfd-1.0.3.dist-info/METADATA
canfd-1.0.3.dist-info/WHEEL
canfd-1.0.3.dist-info/top_level.txt
canfd-1.0.3.dist-info/RECORD
