Metadata-Version: 2.4
Name: canfd
Version: 1.0.3
Summary: Python CAN-FD access module
Home-page: https://item.taobao.com/item.htm?id=610739408298&pisk=gk1ibhvShOJs2NZpp6O_UqNW8L2L1COXmihvDIK4LH-I6id9MB7ePElZgAJqL9b5mhUbCCBHmMSHbibb5E-V0ixABJFR5NOXguK0w7Q_KdFldGcwbBz2PEkaJd8WeRtwguE8wv3eCldVDhKkTWkePH8wuh84-p86zI8wQFzHYEYS3cSV0yxe5U8q3jJZYv8XYx8wgf-UTUTq0EkZgybeAER20iJa-wlW80K5Q1CUvc3ZsyTX16YMI373FjlcPbpw4sKEgu5HSQtP7Hcqg3xvIkQhWlc5JC1lqUITTfjlP6sH8gP0xIsC3i8cY7iv1TI1NpbQUX7BsH9P3p4a_wAMjLYpKqM9stS1id6ilz_e_M6WVdyQAefOwKxWKDrNJwxwEtjTAj-OEwSHe6nKwIsC3i8cYcjPQvkySdlX8rCEhx9wRexJG15
Author: codenocold
Author-email: codenocold@gmail.com
License: BSD
Keywords: CAN-FD,USB-CAN
Requires-Python: >=3
Requires-Dist: pyserial==3.5
Dynamic: author
Dynamic: author-email
Dynamic: home-page
Dynamic: keywords
Dynamic: license
Dynamic: requires-dist
Dynamic: requires-python
Dynamic: summary
